jd_HTMLTestRunner/HTMLTestRunner.py
jd_HTMLTestRunner/__init__.py
jd_HTMLTestRunner-1.7.0.dist-info/LICENSE
jd_HTMLTestRunner-1.7.0.dist-info/METADATA
jd_HTMLTestRunner-1.7.0.dist-info/WHEEL
jd_HTMLTestRunner-1.7.0.dist-info/top_level.txt
jd_HTMLTestRunner-1.7.0.dist-info/RECORD
