Metadata-Version: 2.1
Name: jd-HTMLTestRunner
Version: 1.7.0
Summary: Python3 Unittest Runner -- HTMLTestRunner
Author-email: wxg001 <wxg001@21cn.com>
License: MIT
Project-URL: Homepage, https://pypi.org/project/jd-HTMLTestRunner/
Project-URL: Bug Tracker, https://pypi.org/project/jd-HTMLTestRunner/
Classifier: Programming Language :: Python :: 3.7
Classifier: Programming Language :: Python :: 3.8
Classifier: Programming Language :: Python :: 3.9
Classifier: Programming Language :: Python :: 3.10
Classifier: License :: OSI Approved :: MIT License
Classifier: Operating System :: OS Independent
Requires-Python: >=3.7
License-File: LICENSE
